[{"d":"DIMAPUR","o":"Agri College B.O","p":"797106","t":"BO","dl":"Delivery","c":"North Eastern Circle","r":"North East - II Region","dv":"Nagaland Division","la":"25.754626600000002","lo":"93.861811599999996"},{"d":"DIMAPUR","o":"Aoyimti B.O","p":"797115","t":"BO","dl":"Delivery","c":"North Eastern Circle","r":"North East - II Region","dv":"Nagaland Division","la":"25.888895000000002","lo":"93.764044999999996"},{"d":"DIMAPUR","o":"Artc S.O","p":"797115","t":"PO","dl":"Delivery","c":"North Eastern Circle","r":"North East - II Region","dv":"Nagaland Division","la":"25.8632160","lo":"93.7543150"},{"d":"DIMAPUR","o":"Chumukedima S.O","p":"797103","t":"PO","dl":"Delivery","c":"North Eastern Circle","r":"North East - II Region","dv":"Nagaland Division","la":"25.8632160","lo":"93.7543150"},{"d":"DIMAPUR","o":"Circular Road S.O","p":"797117","t":"PO","dl":"Delivery","c":"North Eastern Circle","r":"North East - II Region","dv":"Nagaland Division","la":"25.8632160","lo":"93.7543150"},{"d":"DIMAPUR","o":"D. C. Complex B.O","p":"797113","t":"BO","dl":"Non Delivery","c":"North Eastern Circle","r":"North East - II Region","dv":"Nagaland Division","la":"NA","lo":"NA"},{"d":"DIMAPUR","o":"Daroga Pathar B.O","p":"797115","t":"BO","dl":"Delivery","c":"North Eastern Circle","r":"North East - II Region","dv":"Nagaland Division","la":"25.8904833","lo":"93.756415000000004"},{"d":"DIMAPUR","o":"Dimapur Bazar S.O","p":"797116","t":"PO","dl":"Delivery","c":"North Eastern Circle","r":"North East - II Region","dv":"Nagaland Division","la":"25.8632160","lo":"93.7543150"},{"d":"DIMAPUR","o":"Dimapur S.O","p":"797112","t":"PO","dl":"Delivery","c":"North Eastern Circle","r":"North East - II Region","dv":"Nagaland Division","la":"25.90583333","lo":"93.73933333"},{"d":"DIMAPUR","o":"Diphupar B.O","p":"797115","t":"BO","dl":"Delivery","c":"North Eastern Circle","r":"North East - II Region","dv":"Nagaland Division","la":"25.869623300000001","lo":"93.768306600000003"},{"d":"DIMAPUR","o":"Doyapur B.O","p":"797112","t":"BO","dl":"Delivery","c":"North Eastern Circle","r":"North East - II Region","dv":"Nagaland Division","la":"25.785946500000001","lo":"93.626177100000007"},{"d":"DIMAPUR","o":"Duncan Basti B.O","p":"797113","t":"BO","dl":"Non Delivery","c":"North Eastern Circle","r":"North East - II Region","dv":"Nagaland Division","la":"NA","lo":"NA"},{"d":"DIMAPUR","o":"Eralibill B.O","p":"797115","t":"BO","dl":"Delivery","c":"North Eastern Circle","r":"North East - II Region","dv":"Nagaland Division","la":"25.888501600000001","lo":"93.776091600000001"},{"d":"DIMAPUR","o":"Hakhizhe B.O","p":"797112","t":"BO","dl":"Delivery","c":"North Eastern Circle","r":"North East - II Region","dv":"Nagaland Division","la":"25.925899999999999","lo":"93.920699999999997"},{"d":"DIMAPUR","o":"Ikishe B.O","p":"797115","t":"BO","dl":"Delivery","c":"North Eastern Circle","r":"North East - II Region","dv":"Nagaland Division","la":"25.8555007","lo":"93.749936399999996"},{"d":"DIMAPUR","o":"Industrial Estate B.O","p":"797113","t":"BO","dl":"Delivery","c":"North Eastern Circle","r":"North East - II Region","dv":"Nagaland Division","la":"25.901890000000002","lo":"93.694204999999997"},{"d":"DIMAPUR","o":"Jharnapani B.O","p":"797106","t":"BO","dl":"Delivery","c":"North Eastern Circle","r":"North East - II Region","dv":"Nagaland Division","la":"25.7566378","lo":"93.843476699999997"},{"d":"DIMAPUR","o":"Kacharigaon","p":"797113","t":"BO","dl":"Delivery","c":"North Eastern Circle","r":"North East - II Region","dv":"Nagaland Division","la":"25.895767110000001","lo":"93.692203070000005"},{"d":"DIMAPUR","o":"Khaibung B.O","p":"797106","t":"BO","dl":"Delivery","c":"North Eastern Circle","r":"North East - II Region","dv":"Nagaland Division","la":"25.683060099999999","lo":"93.857288199999999"},{"d":"DIMAPUR","o":"Khehekhu B.O","p":"797116","t":"BO","dl":"Delivery","c":"North Eastern Circle","r":"North East - II Region","dv":"Nagaland Division","la":"25.791636799999999","lo":"93.802191699999995"},{"d":"DIMAPUR","o":"Khermahal B.O","p":"797112","t":"BO","dl":"Non Delivery","c":"North Eastern Circle","r":"North East - II Region","dv":"Nagaland Division","la":"NA","lo":"NA"},{"d":"DIMAPUR","o":"Khoponalla B.O","p":"797103","t":"BO","dl":"Delivery","c":"North Eastern Circle","r":"North East - II Region","dv":"Nagaland Division","la":"25.801090299999998","lo":"93.745046400000007"},{"d":"DIMAPUR","o":"Kuda B.O","p":"797112","t":"BO","dl":"Delivery","c":"North Eastern Circle","r":"North East - II Region","dv":"Nagaland Division","la":"25.8907667","lo":"93.737622000000002"},{"d":"DIMAPUR","o":"Kuhuboto B.O","p":"797116","t":"BO","dl":"Delivery","c":"North Eastern Circle","r":"North East - II Region","dv":"Nagaland Division","la":"25.931607899999999","lo":"93.753224399999993"},{"d":"DIMAPUR","o":"Kushiabill B.O","p":"797116","t":"BO","dl":"Delivery","c":"North Eastern Circle","r":"North East - II Region","dv":"Nagaland Division","la":"25.938963699999999","lo":"93.753428200000002"},{"d":"DIMAPUR","o":"Lengrijan B.O","p":"797113","t":"BO","dl":"Delivery","c":"North Eastern Circle","r":"North East - II Region","dv":"Nagaland Division","la":"25.909916599999999","lo":"93.693886599999999"},{"d":"DIMAPUR","o":"Medziphema S.O","p":"797106","t":"PO","dl":"Delivery","c":"North Eastern Circle","r":"North East - II Region","dv":"Nagaland Division","la":"25.8632160","lo":"93.7543150"},{"d":"DIMAPUR","o":"New Nepaligaon S.O","p":"797113","t":"PO","dl":"Delivery","c":"North Eastern Circle","r":"North East - II Region","dv":"Nagaland Division","la":"25.8632160","lo":"93.7543150"},{"d":"DIMAPUR","o":"Nihekhu B.O","p":"797103","t":"BO","dl":"Delivery","c":"North Eastern Circle","r":"North East - II Region","dv":"Nagaland Division","la":"25.864706000000002","lo":"93.934488000000002"},{"d":"DIMAPUR","o":"Nuiland B.O","p":"797112","t":"BO","dl":"Delivery","c":"North Eastern Circle","r":"North East - II Region","dv":"Nagaland Division","la":"25.909060100000001","lo":"93.989285199999998"},{"d":"DIMAPUR","o":"P C College B.O","p":"797103","t":"BO","dl":"Delivery","c":"North Eastern Circle","r":"North East - II Region","dv":"Nagaland Division","la":"25.8053563","lo":"93.801750299999995"},{"d":"DIMAPUR","o":"Padampukhuri B.O","p":"797116","t":"BO","dl":"Delivery","c":"North Eastern Circle","r":"North East - II Region","dv":"Nagaland Division","la":"25.868410900000001","lo":"93.751015499999994"},{"d":"DIMAPUR","o":"Phaipijan B.O","p":"797112","t":"BO","dl":"Delivery","c":"North Eastern Circle","r":"North East - II Region","dv":"Nagaland Division","la":"25.888974999999999","lo":"93.745784999999998"},{"d":"DIMAPUR","o":"Pherima B.O","p":"797106","t":"BO","dl":"Delivery","c":"North Eastern Circle","r":"North East - II Region","dv":"Nagaland Division","la":"25.775248300000001","lo":"93.920058299999994"},{"d":"DIMAPUR","o":"Pimla B.O","p":"797103","t":"BO","dl":"Delivery","c":"North Eastern Circle","r":"North East - II Region","dv":"Nagaland Division","la":"25.708769","lo":"93.653841999999997"},{"d":"DIMAPUR","o":"Piphema B.O","p":"797106","t":"BO","dl":"Delivery","c":"North Eastern Circle","r":"North East - II Region","dv":"Nagaland Division","la":"25.748698300000001","lo":"93.957904999999997"},{"d":"DIMAPUR","o":"Pwd Colony B.O","p":"797117","t":"BO","dl":"Non Delivery","c":"North Eastern Circle","r":"North East - II Region","dv":"Nagaland Division","la":"NA","lo":"NA"},{"d":"DIMAPUR","o":"Rangapahar B.O","p":"797118","t":"BO","dl":"Delivery","c":"North Eastern Circle","r":"North East - II Region","dv":"Nagaland Division","la":"25.855355200000002","lo":"93.7104961"},{"d":"DIMAPUR","o":"Razaphema B.O","p":"797106","t":"BO","dl":"Delivery","c":"North Eastern Circle","r":"North East - II Region","dv":"Nagaland Division","la":"25.689187100000002","lo":"93.776451600000001"},{"d":"DIMAPUR","o":"Seluophe BO","p":"797112","t":"BO","dl":"Delivery","c":"North Eastern Circle","r":"North East - II Region","dv":"Nagaland Division","la":"25.843522","lo":"93.727628800000005"},{"d":"DIMAPUR","o":"Showba Old B.O","p":"797115","t":"BO","dl":"Delivery","c":"North Eastern Circle","r":"North East - II Region","dv":"Nagaland Division","la":"25.7917694","lo":"93.808357599999994"},{"d":"DIMAPUR","o":"Signal Village","p":"797118","t":"PO","dl":"Delivery","c":"North Eastern Circle","r":"North East - II Region","dv":"Nagaland Division","la":"25.6707778","lo":"94.1075833"},{"d":"DIMAPUR","o":"Singrijan B.O","p":"797112","t":"BO","dl":"Delivery","c":"North Eastern Circle","r":"North East - II Region","dv":"Nagaland Division","la":"25.842363299999999","lo":"93.724069999999998"},{"d":"DIMAPUR","o":"Sirhima B.O","p":"797106","t":"BO","dl":"Delivery","c":"North Eastern Circle","r":"North East - II Region","dv":"Nagaland Division","la":"25.7121107","lo":"93.875744499999996"},{"d":"DIMAPUR","o":"Suger Mill B.O","p":"797115","t":"BO","dl":"Delivery","c":"North Eastern Circle","r":"North East - II Region","dv":"Nagaland Division","la":"25.8461839","lo":"93.771806999999995"},{"d":"DIMAPUR","o":"Sukhovi B.O","p":"797115","t":"BO","dl":"Delivery","c":"North Eastern Circle","r":"North East - II Region","dv":"Nagaland Division","la":"25.749171400000002","lo":"93.694564999999997"},{"d":"DIMAPUR","o":"Tenyiphe B.O","p":"797103","t":"BO","dl":"Delivery","c":"North Eastern Circle","r":"North East - II Region","dv":"Nagaland Division","la":"25.830596199999999","lo":"93.775602899999996"},{"d":"DIMAPUR","o":"Thahekhu B.O","p":"797118","t":"BO","dl":"Delivery","c":"North Eastern Circle","r":"North East - II Region","dv":"Nagaland Division","la":"25.882923900000002","lo":"93.721470699999998"},{"d":"DIMAPUR","o":"Toulazouma","p":"797115","t":"BO","dl":"Delivery","c":"North Eastern Circle","r":"North East - II Region","dv":"Nagaland Division","la":"25.866980160000001","lo":"93.731557800000004"},{"d":"DIMAPUR","o":"Vihokhu B.O","p":"797116","t":"BO","dl":"Delivery","c":"North Eastern Circle","r":"North East - II Region","dv":"Nagaland Division","la":"25.867654399999999","lo":"93.865741499999999"},{"d":"DIMAPUR","o":"Zeliangrong B.O","p":"797117","t":"BO","dl":"Non Delivery","c":"North Eastern Circle","r":"North East - II Region","dv":"Nagaland Division","la":"NA","lo":"NA"},{"d":"KIPHIRE","o":"Amahatore B.O","p":"798611","t":"BO","dl":"Delivery","c":"North Eastern Circle","r":"North East - II Region","dv":"Nagaland Division","la":"25.940970700000001","lo":"94.735403399999996"},{"d":"KIPHIRE","o":"Anatongere B.O","p":"798611","t":"BO","dl":"Delivery","c":"North Eastern Circle","r":"North East - II Region","dv":"Nagaland Division","la":"25.9722145","lo":"94.828657000000007"},{"d":"KIPHIRE","o":"Kiphire S.O","p":"798611","t":"PO","dl":"Delivery","c":"North Eastern Circle","r":"North East - II Region","dv":"Nagaland Division","la":"25.8484810","lo":"94.8742460"},{"d":"KIPHIRE","o":"Kisethong B.O","p":"798611","t":"BO","dl":"Delivery","c":"North Eastern Circle","r":"North East - II Region","dv":"Nagaland Division","la":"25.9675066","lo":"94.703353300000003"},{"d":"KIPHIRE","o":"Kiusam","p":"798611","t":"BO","dl":"Delivery","c":"North Eastern Circle","r":"North East - II Region","dv":"Nagaland Division","la":"25.92603175","lo":"94.899063990000002"},{"d":"KIPHIRE","o":"Longmatra B.O","p":"798611","t":"BO","dl":"Delivery","c":"North Eastern Circle","r":"North East - II Region","dv":"Nagaland Division","la":"25.7886633","lo":"94.745826600000001"},{"d":"KIPHIRE","o":"Mimi","p":"798611","t":"BO","dl":"Delivery","c":"North Eastern Circle","r":"North East - II Region","dv":"Nagaland Division","la":"25.710000000000001","lo":"94.905900000000003"},{"d":"KIPHIRE","o":"Moya B.O","p":"798611","t":"BO","dl":"Delivery","c":"North Eastern Circle","r":"North East - II Region","dv":"Nagaland Division","la":"25.77702","lo":"94.848506599999993"},{"d":"KIPHIRE","o":"Penkim","p":"798611","t":"BO","dl":"Delivery","c":"North Eastern Circle","r":"North East - II Region","dv":"Nagaland Division","la":"25.799900000000001","lo":"94.911299999999997"},{"d":"KIPHIRE","o":"Phalonger B.O","p":"798611","t":"BO","dl":"Delivery","c":"North Eastern Circle","r":"North East - II Region","dv":"Nagaland Division","la":"25.924779999999998","lo":"94.815346599999998"},{"d":"KIPHIRE","o":"Phisami B.O","p":"798611","t":"BO","dl":"Delivery","c":"North Eastern Circle","r":"North East - II Region","dv":"Nagaland Division","la":"25.999578499999998","lo":"94.679621100000006"},{"d":"KIPHIRE","o":"Pokhpur B.O","p":"798611","t":"BO","dl":"Delivery","c":"North Eastern Circle","r":"North East - II Region","dv":"Nagaland Division","la":"25.879833000000001","lo":"94.942194499999999"},{"d":"KIPHIRE","o":"Pungro B.O","p":"798611","t":"BO","dl":"Delivery","c":"North Eastern Circle","r":"North East - II Region","dv":"Nagaland Division","la":"25.813106600000001","lo":"94.844893299999995"},{"d":"KIPHIRE","o":"Sangkhumti","p":"798611","t":"BO","dl":"Delivery","c":"North Eastern Circle","r":"North East - II Region","dv":"Nagaland Division","la":"25.922242229999998","lo":"94.856900199999998"},{"d":"KIPHIRE","o":"Sikur B.O","p":"798611","t":"BO","dl":"Delivery","c":"North Eastern Circle","r":"North East - II Region","dv":"Nagaland Division","la":"25.994044899999999","lo":"94.858566600000003"},{"d":"KIPHIRE","o":"Singrup B.O","p":"798611","t":"BO","dl":"Delivery","c":"North Eastern Circle","r":"North East - II Region","dv":"Nagaland Division","la":"25.914142900000002","lo":"94.752084400000001"},{"d":"KIPHIRE","o":"Siochang B.O","p":"798611","t":"BO","dl":"Delivery","c":"North Eastern Circle","r":"North East - II Region","dv":"Nagaland Division","la":"25.923422599999999","lo":"94.644427800000003"},{"d":"KIPHIRE","o":"Sitimi B.O","p":"798611","t":"BO","dl":"Delivery","c":"North Eastern Circle","r":"North East - II Region","dv":"Nagaland Division","la":"25.8401666","lo":"94.684173299999998"},{"d":"KIPHIRE","o":"Thanamir","p":"798611","t":"BO","dl":"Delivery","c":"North Eastern Circle","r":"North East - II Region","dv":"Nagaland Division","la":"25.7773","lo":"94.9542"},{"d":"KIPHIRE","o":"Tsunger","p":"798611","t":"BO","dl":"Delivery","c":"North Eastern Circle","r":"North East - II Region","dv":"Nagaland Division","la":"25.893556790000002","lo":"94.676940950000002"},{"d":"KIPHIRE","o":"Zaonger","p":"798611","t":"BO","dl":"Delivery","c":"North Eastern Circle","r":"North East - II Region","dv":"Nagaland Division","la":"25.857365049999999","lo":"94.880955439999994"},{"d":"KOHIMA","o":"Asukika B.O","p":"797109","t":"BO","dl":"Delivery","c":"North Eastern Circle","r":"North East - II Region","dv":"Nagaland Division","la":"25.977465899999999","lo":"94.305334799999997"},{"d":"KOHIMA","o":"Botsa B.O","p":"797105","t":"BO","dl":"Delivery","c":"North Eastern Circle","r":"North East - II Region","dv":"Nagaland Division","la":"25.8564069","lo":"94.158672199999998"},{"d":"KOHIMA","o":"Chakhabama B.O","p":"797003","t":"BO","dl":"Delivery","c":"North Eastern Circle","r":"North East - II Region","dv":"Nagaland Division","la":"25.6144374","lo":"94.116280799999998"},{"d":"KOHIMA","o":"Chedema B.O","p":"797003","t":"BO","dl":"Delivery","c":"North Eastern Circle","r":"North East - II Region","dv":"Nagaland Division","la":"25.6820916","lo":"94.142378300000004"},{"d":"KOHIMA","o":"Chiechama S.O","p":"797105","t":"PO","dl":"Delivery","c":"North Eastern Circle","r":"North East - II Region","dv":"Nagaland Division","la":"25.6707778","lo":"94.1075833"},{"d":"KOHIMA","o":"Chiephobozou B.O","p":"797105","t":"BO","dl":"Delivery","c":"North Eastern Circle","r":"North East - II Region","dv":"Nagaland Division","la":"25.795826999999999","lo":"94.130206099999995"},{"d":"KOHIMA","o":"Ciesema B.O","p":"797003","t":"BO","dl":"Delivery","c":"North Eastern Circle","r":"North East - II Region","dv":"Nagaland Division","la":"25.743313300000001","lo":"94.088930000000005"},{"d":"KOHIMA","o":"Dihoma B.O","p":"797003","t":"BO","dl":"Delivery","c":"North Eastern Circle","r":"North East - II Region","dv":"Nagaland Division","la":"25.735786600000001","lo":"94.1965"},{"d":"KOHIMA","o":"Ehunnu B.O","p":"797109","t":"BO","dl":"Delivery","c":"North Eastern Circle","r":"North East - II Region","dv":"Nagaland Division","la":"25.969166600000001","lo":"94.273926599999996"},{"d":"KOHIMA","o":"Jakhama S.O","p":"797006","t":"PO","dl":"Delivery","c":"North Eastern Circle","r":"North East - II Region","dv":"Nagaland Division","la":"25.5911405","lo":"94.1239288"},{"d":"KOHIMA","o":"Jotsoma B.O","p":"797002","t":"BO","dl":"Delivery","c":"North Eastern Circle","r":"North East - II Region","dv":"Nagaland Division","la":"25.673091599999999","lo":"94.064053299999998"},{"d":"KOHIMA","o":"Kandinu B.O","p":"797109","t":"BO","dl":"Delivery","c":"North Eastern Circle","r":"North East - II Region","dv":"Nagaland Division","la":"26.0044","lo":"94.261183299999999"},{"d":"KOHIMA","o":"Kedima B.O","p":"797006","t":"BO","dl":"Delivery","c":"North Eastern Circle","r":"North East - II Region","dv":"Nagaland Division","la":"25.557185","lo":"94.178556599999993"},{"d":"KOHIMA","o":"Khonoma B.O","p":"797002","t":"BO","dl":"Delivery","c":"North Eastern Circle","r":"North East - II Region","dv":"Nagaland Division","la":"25.651758300000001","lo":"94.022143299999996"},{"d":"KOHIMA","o":"Khuzama B.O","p":"797006","t":"BO","dl":"Delivery","c":"North Eastern Circle","r":"North East - II Region","dv":"Nagaland Division","la":"25.5347717","lo":"94.135383500000003"},{"d":"KOHIMA","o":"Kigwema B.O","p":"797006","t":"BO","dl":"Delivery","c":"North Eastern Circle","r":"North East - II Region","dv":"Nagaland Division","la":"25.607969300000001","lo":"94.128234000000006"},{"d":"KOHIMA","o":"Kijumetouma","p":"797003","t":"BO","dl":"Delivery","c":"North Eastern Circle","r":"North East - II Region","dv":"Nagaland Division","la":"25.775639999999999","lo":"94.240539999999996"},{"d":"KOHIMA","o":"Kizocha B.O","p":"797003","t":"BO","dl":"Delivery","c":"North Eastern Circle","r":"North East - II Region","dv":"Nagaland Division","la":"25.591921599999999","lo":"94.185843300000002"},{"d":"KOHIMA","o":"Kohima H.O","p":"797001","t":"HO","dl":"Delivery","c":"North Eastern Circle","r":"North East - II Region","dv":"Nagaland Division","la":"25.67077778","lo":"94.10758333"},{"d":"KOHIMA","o":"Kohima Science College S.O","p":"797002","t":"PO","dl":"Delivery","c":"North Eastern Circle","r":"North East - II Region","dv":"Nagaland Division","la":"25.6707778","lo":"94.1075833"},{"d":"KOHIMA","o":"Kohima Village S.O","p":"797003","t":"PO","dl":"Delivery","c":"North Eastern Circle","r":"North East - II Region","dv":"Nagaland Division","la":"25.6707778","lo":"94.1075833"},{"d":"KOHIMA","o":"Lalmati B.O","p":"797120","t":"BO","dl":"Delivery","c":"North Eastern Circle","r":"North East - II Region","dv":"Nagaland Division","la":"25.738786600000001","lo":"94.008666599999998"},{"d":"KOHIMA","o":"Meriema B.O","p":"797004","t":"BO","dl":"Delivery","c":"North Eastern Circle","r":"North East - II Region","dv":"Nagaland Division","la":"25.724565500000001","lo":"94.095644500000006"},{"d":"KOHIMA","o":"Mezoma B.O","p":"797002","t":"BO","dl":"Delivery","c":"North Eastern Circle","r":"North East - II Region","dv":"Nagaland Division","la":"25.675661600000002","lo":"94.019181599999996"},{"d":"KOHIMA","o":"Mima B.O","p":"797006","t":"BO","dl":"Delivery","c":"North Eastern Circle","r":"North East - II Region","dv":"Nagaland Division","la":"25.609945","lo":"94.143041600000004"},{"d":"KOHIMA","o":"Monkhola S.O","p":"797121","t":"PO","dl":"Delivery","c":"North Eastern Circle","r":"North East - II Region","dv":"Nagaland Division","la":"25.6707778","lo":"94.1075833"},{"d":"KOHIMA","o":"New Sectt Complex S.O","p":"797004","t":"PO","dl":"Delivery","c":"North Eastern Circle","r":"North East - II Region","dv":"Nagaland Division","la":"25.6707778","lo":"94.1075833"},{"d":"KOHIMA","o":"Noklak SO","p":"798626","t":"PO","dl":"Delivery","c":"North Eastern Circle","r":"North East - II Region","dv":"Nagaland Division","la":"26.20128855","lo":"95.01892209"},{"d":"KOHIMA","o":"Nsunyu B.O","p":"797109","t":"BO","dl":"Delivery","c":"North Eastern Circle","r":"North East - II Region","dv":"Nagaland Division","la":"25.981816599999998","lo":"94.239866599999999"},{"d":"KOHIMA","o":"P.R Hill S.O","p":"797120","t":"PO","dl":"Delivery","c":"North Eastern Circle","r":"North East - II Region","dv":"Nagaland Division","la":"25.6587","lo":"94.0974"},{"d":"KOHIMA","o":"Pfuchama","p":"797120","t":"BO","dl":"Delivery","c":"North Eastern Circle","r":"North East - II Region","dv":"Nagaland Division","la":"25.6206882","lo":"94.087434999999999"},{"d":"KOHIMA","o":"Phekerkriema","p":"797105","t":"BO","dl":"Delivery","c":"North Eastern Circle","r":"North East - II Region","dv":"Nagaland Division","la":"25.88128","lo":"94.021860000000004"},{"d":"KOHIMA","o":"Phenshunyu B.O","p":"797109","t":"BO","dl":"Delivery","c":"North Eastern Circle","r":"North East - II Region","dv":"Nagaland Division","la":"25.9326601","lo":"94.165133699999998"},{"d":"KOHIMA","o":"Phenwhenyu B.O","p":"797109","t":"BO","dl":"Delivery","c":"North Eastern Circle","r":"North East - II Region","dv":"Nagaland Division","la":"25.888899899999998","lo":"94.201790000000003"},{"d":"KOHIMA","o":"Phesama B.O","p":"797120","t":"BO","dl":"Delivery","c":"North Eastern Circle","r":"North East - II Region","dv":"Nagaland Division","la":"25.627021599999999","lo":"94.113849000000002"},{"d":"KOHIMA","o":"Pungro","p":"798617","t":"PO","dl":"Delivery","c":"North Eastern Circle","r":"North East - II Region","dv":"Nagaland Division","la":"12.16680556","lo":"77.10655556"},{"d":"KOHIMA","o":"Rusoma B.O","p":"797003","t":"BO","dl":"Delivery","c":"North Eastern Circle","r":"North East - II Region","dv":"Nagaland Division","la":"25.725698300000001","lo":"94.138128300000005"},{"d":"KOHIMA","o":"Sendenyu B.O","p":"797109","t":"BO","dl":"Delivery","c":"North Eastern Circle","r":"North East - II Region","dv":"Nagaland Division","la":"25.906141600000002","lo":"94.121711599999998"},{"d":"KOHIMA","o":"Shamator SO","p":"798628","t":"PO","dl":"Delivery","c":"North Eastern Circle","r":"North East - II Region","dv":"Nagaland Division","la":"26.0733066","lo":"94.869835"},{"d":"KOHIMA","o":"Tesophenyu B.O","p":"797109","t":"BO","dl":"Delivery","c":"North Eastern Circle","r":"North East - II Region","dv":"Nagaland Division","la":"25.972316599999999","lo":"94.212133300000005"},{"d":"KOHIMA","o":"Thizama B.O","p":"797004","t":"BO","dl":"Delivery","c":"North Eastern Circle","r":"North East - II Region","dv":"Nagaland Division","la":"25.745589500000001","lo":"94.108727500000001"},{"d":"KOHIMA","o":"Tseminyu Old Town B.O","p":"797109","t":"BO","dl":"Delivery","c":"North Eastern Circle","r":"North East - II Region","dv":"Nagaland Division","la":"25.898018799999999","lo":"94.182481199999998"},{"d":"KOHIMA","o":"Tseminyu S.O","p":"797109","t":"PO","dl":"Delivery","c":"North Eastern Circle","r":"North East - II Region","dv":"Nagaland Division","la":"25.6707778","lo":"94.1075833"},{"d":"KOHIMA","o":"Tsosesunyu B.O","p":"797109","t":"BO","dl":"Delivery","c":"North Eastern Circle","r":"North East - II Region","dv":"Nagaland Division","la":"25.9097723","lo":"94.030169900000004"},{"d":"KOHIMA","o":"Tuophema B.O","p":"797105","t":"BO","dl":"Delivery","c":"North Eastern Circle","r":"North East - II Region","dv":"Nagaland Division","la":"25.845258399999999","lo":"94.178229900000005"},{"d":"KOHIMA","o":"Viphoma","p":"797105","t":"BO","dl":"Delivery","c":"North Eastern Circle","r":"North East - II Region","dv":"Nagaland Division","la":"25.824047","lo":"93.987243899999996"},{"d":"KOHIMA","o":"Viswema B.O","p":"797006","t":"BO","dl":"Delivery","c":"North Eastern Circle","r":"North East - II Region","dv":"Nagaland Division","la":"25.559217799999999","lo":"94.142570599999999"},{"d":"KOHIMA","o":"Zephenyu B.O","p":"797109","t":"BO","dl":"Delivery","c":"North Eastern Circle","r":"North East - II Region","dv":"Nagaland Division","la":"25.943081599999999","lo":"94.2198049"},{"d":"KOHIMA","o":"Zhadima B.O","p":"797105","t":"BO","dl":"Delivery","c":"North Eastern Circle","r":"North East - II Region","dv":"Nagaland Division","la":"25.8005912","lo":"94.063990899999993"},{"d":"KOHIMA","o":"Zubza B.O","p":"797120","t":"BO","dl":"Delivery","c":"North Eastern Circle","r":"North East - II Region","dv":"Nagaland Division","la":"25.712395000000001","lo":"94.040923300000003"},{"d":"LONGLENG","o":"Bhumnyu BO","p":"798625","t":"BO","dl":"Delivery","c":"North Eastern Circle","r":"North East - II Region","dv":"Nagaland Division","la":"26.5215566","lo":"94.844591600000001"},{"d":"LONGLENG","o":"Hukpang B.O","p":"798625","t":"BO","dl":"Delivery","c":"North Eastern Circle","r":"North East - II Region","dv":"Nagaland Division","la":"26.472696599999999","lo":"94.807154999999995"},{"d":"LONGLENG","o":"Longleng S.O","p":"798625","t":"PO","dl":"Delivery","c":"North Eastern Circle","r":"North East - II Region","dv":"Nagaland Division","la":"26.4903840","lo":"94.8196990"},{"d":"LONGLENG","o":"Mongtikong","p":"798625","t":"BO","dl":"Delivery","c":"North Eastern Circle","r":"North East - II Region","dv":"Nagaland Division","la":"26.452923309999999","lo":"94.720413629999996"},{"d":"LONGLENG","o":"Nian B.O","p":"798625","t":"BO","dl":"Delivery","c":"North Eastern Circle","r":"North East - II Region","dv":"Nagaland Division","la":"26.595767599999999","lo":"94.8596608"},{"d":"LONGLENG","o":"Phomching B.O","p":"798625","t":"BO","dl":"Delivery","c":"North Eastern Circle","r":"North East - II Region","dv":"Nagaland Division","la":"26.4639633","lo":"94.772458299999997"},{"d":"LONGLENG","o":"Sakchi B.O","p":"798625","t":"BO","dl":"Delivery","c":"North Eastern Circle","r":"North East - II Region","dv":"Nagaland Division","la":"26.405021600000001","lo":"94.863641599999994"},{"d":"LONGLENG","o":"Yachem B.O","p":"798625","t":"BO","dl":"Delivery","c":"North Eastern Circle","r":"North East - II Region","dv":"Nagaland Division","la":"26.520466299999999","lo":"94.721862900000005"},{"d":"LONGLENG","o":"Yongphang","p":"798625","t":"BO","dl":"Delivery","c":"North Eastern Circle","r":"North East - II Region","dv":"Nagaland Division","la":"26.450346360000001","lo":"94.842335869999999"},{"d":"LONGLENG","o":"Yongshei","p":"798625","t":"BO","dl":"Delivery","c":"North Eastern Circle","r":"North East - II Region","dv":"Nagaland Division","la":"26.562026840000001","lo":"94.777034040000004"},{"d":"LONGLENG","o":"Yongyak B.O","p":"798625","t":"BO","dl":"Delivery","c":"North Eastern Circle","r":"North East - II Region","dv":"Nagaland Division","la":"26.587204","lo":"94.8059224"},{"d":"MOKOKCHUNG","o":"Akumen","p":"798604","t":"BO","dl":"Delivery","c":"North Eastern Circle","r":"North East - II Region","dv":"Nagaland Division","la":"26.618471","lo":"94.436081000000001"},{"d":"MOKOKCHUNG","o":"Alichen S.O","p":"798607","t":"PO","dl":"Delivery","c":"North Eastern Circle","r":"North East - II Region","dv":"Nagaland Division","la":"26.273415","lo":"94.456705"},{"d":"MOKOKCHUNG","o":"Alungkima B.O","p":"798604","t":"BO","dl":"Delivery","c":"North Eastern Circle","r":"North East - II Region","dv":"Nagaland Division","la":"26.5428064","lo":"94.516261299999996"},{"d":"MOKOKCHUNG","o":"Alungtaki B.O","p":"798604","t":"BO","dl":"Delivery","c":"North Eastern Circle","r":"North East - II Region","dv":"Nagaland Division","la":"26.499403300000001","lo":"94.439026600000005"},{"d":"MOKOKCHUNG","o":"Anaki","p":"798623","t":"BO","dl":"Delivery","c":"North Eastern Circle","r":"North East - II Region","dv":"Nagaland Division","la":"26.685789","lo":"94.711815000000001"},{"d":"MOKOKCHUNG","o":"Aolijen B.O","p":"798601","t":"BO","dl":"Delivery","c":"North Eastern Circle","r":"North East - II Region","dv":"Nagaland Division","la":"26.29297","lo":"94.482626600000003"},{"d":"MOKOKCHUNG","o":"Aonokpu","p":"798604","t":"BO","dl":"Delivery","c":"North Eastern Circle","r":"North East - II Region","dv":"Nagaland Division","la":"26.598665","lo":"94.486473000000004"},{"d":"MOKOKCHUNG","o":"Asangma B.O","p":"798618","t":"BO","dl":"Delivery","c":"North Eastern Circle","r":"North East - II Region","dv":"Nagaland Division","la":"26.558415","lo":"94.591785000000002"},{"d":"MOKOKCHUNG","o":"Barakangtsung B.O","p":"798618","t":"BO","dl":"Delivery","c":"North Eastern Circle","r":"North East - II Region","dv":"Nagaland Division","la":"26.705460599999999","lo":"94.706268699999995"},{"d":"MOKOKCHUNG","o":"Changki B.O","p":"798601","t":"BO","dl":"Delivery","c":"North Eastern Circle","r":"North East - II Region","dv":"Nagaland Division","la":"26.422666599999999","lo":"94.39058"},{"d":"MOKOKCHUNG","o":"Chantongia S.O","p":"798613","t":"PO","dl":"Delivery","c":"North Eastern Circle","r":"North East - II Region","dv":"Nagaland Division","la":"26.3220740","lo":"94.5144800"},{"d":"MOKOKCHUNG","o":"Chuchuyimlang S.O","p":"798614","t":"PO","dl":"Delivery","c":"North Eastern Circle","r":"North East - II Region","dv":"Nagaland Division","la":"26.3220740","lo":"94.5144800"},{"d":"MOKOKCHUNG","o":"Chungtia B.O","p":"798601","t":"BO","dl":"Delivery","c":"North Eastern Circle","r":"North East - II Region","dv":"Nagaland Division","la":"26.386968400000001","lo":"94.441791800000004"},{"d":"MOKOKCHUNG","o":"Chungtia Yimsen B.O","p":"798604","t":"BO","dl":"Delivery","c":"North Eastern Circle","r":"North East - II Region","dv":"Nagaland Division","la":"26.4994549","lo":"94.439063300000001"},{"d":"MOKOKCHUNG","o":"Fazl Ali College B.O","p":"798601","t":"BO","dl":"Delivery","c":"North Eastern Circle","r":"North East - II Region","dv":"Nagaland Division","la":"26.33202","lo":"94.553020000000004"},{"d":"MOKOKCHUNG","o":"Impur S.O","p":"798615","t":"PO","dl":"Delivery","c":"North Eastern Circle","r":"North East - II Region","dv":"Nagaland Division","la":"26.3220740","lo":"94.5144800"},{"d":"MOKOKCHUNG","o":"Khari B.O","p":"798604","t":"BO","dl":"Delivery","c":"North Eastern Circle","r":"North East - II Region","dv":"Nagaland Division","la":"26.499496600000001","lo":"94.438984899999994"},{"d":"MOKOKCHUNG","o":"Khensa B.O","p":"798601","t":"BO","dl":"Delivery","c":"North Eastern Circle","r":"North East - II Region","dv":"Nagaland Division","la":"26.345590000000001","lo":"94.488275000000002"},{"d":"MOKOKCHUNG","o":"Kubulong B.O","p":"798615","t":"BO","dl":"Delivery","c":"North Eastern Circle","r":"North East - II Region","dv":"Nagaland Division","la":"26.413906399999998","lo":"94.533983300000003"},{"d":"MOKOKCHUNG","o":"Kubza B.O","p":"798601","t":"BO","dl":"Delivery","c":"North Eastern Circle","r":"North East - II Region","dv":"Nagaland Division","la":"26.3244933","lo":"94.448533299999994"},{"d":"MOKOKCHUNG","o":"Longchem B.O","p":"798604","t":"BO","dl":"Delivery","c":"North Eastern Circle","r":"North East - II Region","dv":"Nagaland Division","la":"26.615433299999999","lo":"94.499899999999997"},{"d":"MOKOKCHUNG","o":"Longjang B.O","p":"798615","t":"BO","dl":"Delivery","c":"North Eastern Circle","r":"North East - II Region","dv":"Nagaland Division","la":"26.458416799999998","lo":"94.552940100000001"},{"d":"MOKOKCHUNG","o":"Longkhum B.O","p":"798607","t":"BO","dl":"Delivery","c":"North Eastern Circle","r":"North East - II Region","dv":"Nagaland Division","la":"26.261576600000001","lo":"94.411881600000001"},{"d":"MOKOKCHUNG","o":"Longkong B.O","p":"798614","t":"BO","dl":"Delivery","c":"North Eastern Circle","r":"North East - II Region","dv":"Nagaland Division","la":"26.390023299999999","lo":"94.616741599999997"},{"d":"MOKOKCHUNG","o":"Longmisa B.O","p":"798601","t":"BO","dl":"Delivery","c":"North Eastern Circle","r":"North East - II Region","dv":"Nagaland Division","la":"26.355255","lo":"94.604113299999995"},{"d":"MOKOKCHUNG","o":"Longnak B.O","p":"798604","t":"BO","dl":"Delivery","c":"North Eastern Circle","r":"North East - II Region","dv":"Nagaland Division","la":"26.499496600000001","lo":"94.439158300000003"},{"d":"MOKOKCHUNG","o":"Longsa B.O","p":"798601","t":"BO","dl":"Delivery","c":"North Eastern Circle","r":"North East - II Region","dv":"Nagaland Division","la":"26.221295000000001","lo":"94.5488316"},{"d":"MOKOKCHUNG","o":"Luyang Valley B.O","p":"798618","t":"BO","dl":"Delivery","c":"North Eastern Circle","r":"North East - II Region","dv":"Nagaland Division","la":"26.667721","lo":"94.640452800000006"},{"d":"MOKOKCHUNG","o":"Mangmentong B.O","p":"798607","t":"BO","dl":"Delivery","c":"North Eastern Circle","r":"North East - II Region","dv":"Nagaland Division","la":"26.291241599999999","lo":"94.398606599999994"},{"d":"MOKOKCHUNG","o":"Merangkong B.O","p":"798618","t":"BO","dl":"Delivery","c":"North Eastern Circle","r":"North East - II Region","dv":"Nagaland Division","la":"26.613307800000001","lo":"94.667057600000007"},{"d":"MOKOKCHUNG","o":"Mokokchung S.O","p":"798601","t":"PO","dl":"Delivery","c":"North Eastern Circle","r":"North East - II Region","dv":"Nagaland Division","la":"26.32469444","lo":"94.51883333"},{"d":"MOKOKCHUNG","o":"Molungkhimong B.O","p":"798618","t":"BO","dl":"Delivery","c":"North Eastern Circle","r":"North East - II Region","dv":"Nagaland Division","la":"26.634924600000002","lo":"94.578005099999999"},{"d":"MOKOKCHUNG","o":"Molungyimsen B.O","p":"798618","t":"BO","dl":"Delivery","c":"North Eastern Circle","r":"North East - II Region","dv":"Nagaland Division","la":"26.631405300000001","lo":"94.583939000000001"},{"d":"MOKOKCHUNG","o":"Mongchen B.O","p":"798604","t":"BO","dl":"Delivery","c":"North Eastern Circle","r":"North East - II Region","dv":"Nagaland Division","la":"26.501380000000001","lo":"94.476511599999995"},{"d":"MOKOKCHUNG","o":"Mongkholemba S.O","p":"798604","t":"PO","dl":"Delivery","c":"North Eastern Circle","r":"North East - II Region","dv":"Nagaland Division","la":"26.3220740","lo":"94.5144800"},{"d":"MOKOKCHUNG","o":"Mongsenyimti B.O","p":"798614","t":"BO","dl":"Delivery","c":"North Eastern Circle","r":"North East - II Region","dv":"Nagaland Division","la":"26.428744999999999","lo":"94.6160833"},{"d":"MOKOKCHUNG","o":"Nst Colony B.O","p":"798601","t":"BO","dl":"Delivery","c":"North Eastern Circle","r":"North East - II Region","dv":"Nagaland Division","la":"26.3290866","lo":"94.530608299999997"},{"d":"MOKOKCHUNG","o":"Ongpangkong B.O","p":"798601","t":"BO","dl":"Delivery","c":"North Eastern Circle","r":"North East - II Region","dv":"Nagaland Division","la":"26.334293299999999","lo":"94.501166600000005"},{"d":"MOKOKCHUNG","o":"Paper Nagar S.O","p":"798623","t":"PO","dl":"Delivery","c":"North Eastern Circle","r":"North East - II Region","dv":"Nagaland Division","la":"26.3220740","lo":"94.5144800"},{"d":"MOKOKCHUNG","o":"Phangsang B.O","p":"798614","t":"BO","dl":"Delivery","c":"North Eastern Circle","r":"North East - II Region","dv":"Nagaland Division","la":"26.4288433","lo":"94.660624999999996"},{"d":"MOKOKCHUNG","o":"S. E. Colony B.O","p":"798601","t":"BO","dl":"Delivery","c":"North Eastern Circle","r":"North East - II Region","dv":"Nagaland Division","la":"26.332381600000001","lo":"94.524769899999995"},{"d":"MOKOKCHUNG","o":"Salulamang B.O","p":"798614","t":"BO","dl":"Delivery","c":"North Eastern Circle","r":"North East - II Region","dv":"Nagaland Division","la":"26.463114999999998","lo":"94.683369999999996"},{"d":"MOKOKCHUNG","o":"Shihaphumi","p":"798604","t":"BO","dl":"Delivery","c":"North Eastern Circle","r":"North East - II Region","dv":"Nagaland Division","la":"26.444447149999998","lo":"94.334804790000007"},{"d":"MOKOKCHUNG","o":"Sungratsu B.O","p":"798615","t":"BO","dl":"Delivery","c":"North Eastern Circle","r":"North East - II Region","dv":"Nagaland Division","la":"26.395006299999999","lo":"94.554059699999996"},{"d":"MOKOKCHUNG","o":"Tamlu B.O","p":"798618","t":"BO","dl":"Delivery","c":"North Eastern Circle","r":"North East - II Region","dv":"Nagaland Division","la":"26.6745606","lo":"94.745758499999994"},{"d":"MOKOKCHUNG","o":"Tuli S.O","p":"798618","t":"PO","dl":"Delivery","c":"North Eastern Circle","r":"North East - II Region","dv":"Nagaland Division","la":"26.3220740","lo":"94.5144800"},{"d":"MOKOKCHUNG","o":"Ungar B.O","p":"798614","t":"BO","dl":"Delivery","c":"North Eastern Circle","r":"North East - II Region","dv":"Nagaland Division","la":"26.4883366","lo":"94.660473300000007"},{"d":"MOKOKCHUNG","o":"Ungma B.O","p":"798601","t":"BO","dl":"Delivery","c":"North Eastern Circle","r":"North East - II Region","dv":"Nagaland Division","la":"26.295193300000001","lo":"94.500868299999993"},{"d":"MOKOKCHUNG","o":"Wamaken B.O","p":"798618","t":"BO","dl":"Delivery","c":"North Eastern Circle","r":"North East - II Region","dv":"Nagaland Division","la":"26.708651499999998","lo":"94.648840199999995"},{"d":"MOKOKCHUNG","o":"Waromung B.O","p":"798604","t":"BO","dl":"Delivery","c":"North Eastern Circle","r":"North East - II Region","dv":"Nagaland Division","la":"26.5589683","lo":"94.530910000000006"},{"d":"MOKOKCHUNG","o":"Yajang C","p":"798623","t":"BO","dl":"Delivery","c":"North Eastern Circle","r":"North East - II Region","dv":"Nagaland Division","la":"26.657800000000002","lo":"94.506200000000007"},{"d":"MOKOKCHUNG","o":"Yaongyimsen B.O","p":"798613","t":"BO","dl":"Delivery","c":"North Eastern Circle","r":"North East - II Region","dv":"Nagaland Division","la":"26.571080299999998","lo":"94.6911123"},{"d":"MOKOKCHUNG","o":"Yisemyong B.O","p":"798614","t":"BO","dl":"Delivery","c":"North Eastern Circle","r":"North East - II Region","dv":"Nagaland Division","la":"26.395665000000001","lo":"94.5958866"},{"d":"MON","o":"Angphang B.O","p":"798603","t":"BO","dl":"Delivery","c":"North Eastern Circle","r":"North East - II Region","dv":"Nagaland Division","la":"26.500913300000001","lo":"94.982953300000005"},{"d":"MON","o":"Baranamsang B.O","p":"798622","t":"BO","dl":"Delivery","c":"North Eastern Circle","r":"North East - II Region","dv":"Nagaland Division","la":"26.705460599999999","lo":"94.706268699999995"},{"d":"MON","o":"Champang S.O","p":"798603","t":"PO","dl":"Delivery","c":"North Eastern Circle","r":"North East - II Region","dv":"Nagaland Division","la":"26.4815740","lo":"94.9926490"},{"d":"MON","o":"Chengloisho B.O","p":"798603","t":"BO","dl":"Delivery","c":"North Eastern Circle","r":"North East - II Region","dv":"Nagaland Division","la":"26.602672599999998","lo":"94.964093399999996"},{"d":"MON","o":"Chenwetnyu B.O","p":"798603","t":"BO","dl":"Delivery","c":"North Eastern Circle","r":"North East - II Region","dv":"Nagaland Division","la":"26.578178999999999","lo":"95.053520300000002"},{"d":"MON","o":"Chingkao B.O","p":"798603","t":"BO","dl":"Delivery","c":"North Eastern Circle","r":"North East - II Region","dv":"Nagaland Division","la":"26.599702700000002","lo":"94.963667599999994"},{"d":"MON","o":"Chinglong B.O","p":"798603","t":"BO","dl":"Delivery","c":"North Eastern Circle","r":"North East - II Region","dv":"Nagaland Division","la":"26.602428","lo":"94.963674299999994"},{"d":"MON","o":"Chui B.O","p":"798621","t":"BO","dl":"Delivery","c":"North Eastern Circle","r":"North East - II Region","dv":"Nagaland Division","la":"26.696760999999999","lo":"95.020779399999995"},{"d":"MON","o":"Jakpang B.O","p":"798603","t":"BO","dl":"Delivery","c":"North Eastern Circle","r":"North East - II Region","dv":"Nagaland Division","la":"26.4614379","lo":"94.931773899999996"},{"d":"MON","o":"Kongon B.O","p":"798622","t":"BO","dl":"Delivery","c":"North Eastern Circle","r":"North East - II Region","dv":"Nagaland Division","la":"26.746258000000001","lo":"94.813873799999996"},{"d":"MON","o":"Longching B.O","p":"798603","t":"BO","dl":"Delivery","c":"North Eastern Circle","r":"North East - II Region","dv":"Nagaland Division","la":"26.5198714","lo":"94.935474400000004"},{"d":"MON","o":"Longpong Senghe B.O","p":"798621","t":"BO","dl":"Delivery","c":"North Eastern Circle","r":"North East - II Region","dv":"Nagaland Division","la":"26.772801600000001","lo":"95.068568299999995"},{"d":"MON","o":"Longwa B.O","p":"798621","t":"BO","dl":"Delivery","c":"North Eastern Circle","r":"North East - II Region","dv":"Nagaland Division","la":"26.666167300000001","lo":"95.188409699999994"},{"d":"MON","o":"Mon S.O","p":"798621","t":"PO","dl":"Delivery","c":"North Eastern Circle","r":"North East - II Region","dv":"Nagaland Division","la":"26.72116667","lo":"95.02677778"},{"d":"MON","o":"Monyakshu B.O","p":"798603","t":"BO","dl":"Delivery","c":"North Eastern Circle","r":"North East - II Region","dv":"Nagaland Division","la":"26.43798","lo":"95.029246599999993"},{"d":"MON","o":"Naginimora S.O","p":"798622","t":"PO","dl":"Delivery","c":"North Eastern Circle","r":"North East - II Region","dv":"Nagaland Division","la":"26.4815740","lo":"94.9926490"},{"d":"MON","o":"Namsa B.O","p":"798602","t":"BO","dl":"Delivery","c":"North Eastern Circle","r":"North East - II Region","dv":"Nagaland Division","la":"26.903286999999999","lo":"95.0826292"},{"d":"MON","o":"Oting","p":"798602","t":"BO","dl":"Delivery","c":"North Eastern Circle","r":"North East - II Region","dv":"Nagaland Division","la":"26.845901019999999","lo":"94.957342879999999"},{"d":"MON","o":"Pessao B.O","p":"798603","t":"BO","dl":"Delivery","c":"North Eastern Circle","r":"North East - II Region","dv":"Nagaland Division","la":"26.40063","lo":"95.045246700000007"},{"d":"MON","o":"Pongkong B.O","p":"798621","t":"BO","dl":"Delivery","c":"North Eastern Circle","r":"North East - II Region","dv":"Nagaland Division","la":"26.764695","lo":"94.919283800000002"},{"d":"MON","o":"Singha Chingnyu B.O","p":"798621","t":"BO","dl":"Delivery","c":"North Eastern Circle","r":"North East - II Region","dv":"Nagaland Division","la":"26.721438299999999","lo":"95.030921599999999"},{"d":"MON","o":"Tang B.O","p":"798621","t":"BO","dl":"Delivery","c":"North Eastern Circle","r":"North East - II Region","dv":"Nagaland Division","la":"26.7078883","lo":"95.114309899999995"},{"d":"MON","o":"Tiru Upper","p":"798602","t":"BO","dl":"Delivery","c":"North Eastern Circle","r":"North East - II Region","dv":"Nagaland Division","la":"26.722075799999999","lo":"95.029206299999998"},{"d":"MON","o":"Tizit S.O","p":"798602","t":"PO","dl":"Delivery","c":"North Eastern Circle","r":"North East - II Region","dv":"Nagaland Division","la":"26.4815740","lo":"94.9926490"},{"d":"MON","o":"Tobu B.O","p":"798603","t":"BO","dl":"Delivery","c":"North Eastern Circle","r":"North East - II Region","dv":"Nagaland Division","la":"26.370046599999998","lo":"94.937443299999998"},{"d":"MON","o":"Totak B.O","p":"798621","t":"BO","dl":"Delivery","c":"North Eastern Circle","r":"North East - II Region","dv":"Nagaland Division","la":"26.666715","lo":"94.995064999999997"},{"d":"MON","o":"Ukha B.O","p":"798603","t":"BO","dl":"Delivery","c":"North Eastern Circle","r":"North East - II Region","dv":"Nagaland Division","la":"26.418456599999999","lo":"94.935366599999995"},{"d":"MON","o":"Wakching B.O","p":"798621","t":"BO","dl":"Delivery","c":"North Eastern Circle","r":"North East - II Region","dv":"Nagaland Division","la":"26.697746599999999","lo":"94.888446599999995"},{"d":"MON","o":"Waunching B.O","p":"798621","t":"BO","dl":"Delivery","c":"North Eastern Circle","r":"North East - II Region","dv":"Nagaland Division","la":"26.6601733","lo":"94.846834999999999"},{"d":"MON","o":"Yannu B.O","p":"798602","t":"BO","dl":"Delivery","c":"North Eastern Circle","r":"North East - II Region","dv":"Nagaland Division","la":"26.874557800000002","lo":"95.170854800000001"},{"d":"MON","o":"Zaboka B.O","p":"798602","t":"BO","dl":"Delivery","c":"North Eastern Circle","r":"North East - II Region","dv":"Nagaland Division","la":"26.933350399999998","lo":"95.143238199999999"},{"d":"MON","o":"Zangkham B.O","p":"798602","t":"BO","dl":"Delivery","c":"North Eastern Circle","r":"North East - II Region","dv":"Nagaland Division","la":"26.804196399999999","lo":"95.158570499999996"},{"d":"Noklak","o":"Chingmei B.O","p":"798612","t":"BO","dl":"Delivery","c":"North Eastern Circle","r":"North East - II Region","dv":"Nagaland Division","la":"26.235684899999999","lo":"94.923431600000001"},{"d":"Noklak","o":"Choklangan B.O","p":"798612","t":"BO","dl":"Delivery","c":"North Eastern Circle","r":"North East - II Region","dv":"Nagaland Division","la":"26.074931599999999","lo":"95.111108299999998"},{"d":"Noklak","o":"Nokhu B.O","p":"798612","t":"BO","dl":"Delivery","c":"North Eastern Circle","r":"North East - II Region","dv":"Nagaland Division","la":"26.239787199999999","lo":"94.8105853"},{"d":"Noklak","o":"Noklak BO","p":"798612","t":"BO","dl":"Delivery","c":"North Eastern Circle","r":"North East - II Region","dv":"Nagaland Division","la":"26.2012885","lo":"95.018922000000003"},{"d":"Noklak","o":"Pangsha B.O","p":"798612","t":"BO","dl":"Delivery","c":"North Eastern Circle","r":"North East - II Region","dv":"Nagaland Division","la":"26.2050956","lo":"95.018835600000003"},{"d":"Noklak","o":"Panso B.O","p":"798612","t":"BO","dl":"Delivery","c":"North Eastern Circle","r":"North East - II Region","dv":"Nagaland Division","la":"26.196439999999999","lo":"95.01688"},{"d":"Noklak","o":"Pessu B.O","p":"798612","t":"BO","dl":"Delivery","c":"North Eastern Circle","r":"North East - II Region","dv":"Nagaland Division","la":"26.196523299999999","lo":"95.016868299999999"},{"d":"Noklak","o":"Sanglao B.O","p":"798612","t":"BO","dl":"Delivery","c":"North Eastern Circle","r":"North East - II Region","dv":"Nagaland Division","la":"26.2294366","lo":"94.8096441"},{"d":"Noklak","o":"Thonokhunyu B.O","p":"798612","t":"BO","dl":"Delivery","c":"North Eastern Circle","r":"North East - II Region","dv":"Nagaland Division","la":"25.989441899999999","lo":"94.905417499999999"},{"d":"PEREN","o":"Athibung B.O","p":"797110","t":"BO","dl":"Delivery","c":"North Eastern Circle","r":"North East - II Region","dv":"Nagaland Division","la":"25.5468683","lo":"93.621914899999993"},{"d":"PEREN","o":"Beisumpuikam","p":"797110","t":"BO","dl":"Delivery","c":"North Eastern Circle","r":"North East - II Region","dv":"Nagaland Division","la":"25.522349299999998","lo":"93.680866609999995"},{"d":"PEREN","o":"Bongkholong B.O","p":"797110","t":"BO","dl":"Delivery","c":"North Eastern Circle","r":"North East - II Region","dv":"Nagaland Division","la":"25.491371699999998","lo":"93.525835999999998"},{"d":"PEREN","o":"Gaili B.O","p":"797110","t":"BO","dl":"Delivery","c":"North Eastern Circle","r":"North East - II Region","dv":"Nagaland Division","la":"25.592987399999998","lo":"93.840871699999994"},{"d":"PEREN","o":"Hening Kunglwa B.O","p":"797112","t":"BO","dl":"Delivery","c":"North Eastern Circle","r":"North East - II Region","dv":"Nagaland Division","la":"25.663445599999999","lo":"93.776985600000003"},{"d":"PEREN","o":"Ikiesingram","p":"797110","t":"BO","dl":"Delivery","c":"North Eastern Circle","r":"North East - II Region","dv":"Nagaland Division","la":"25.470493579999999","lo":"93.46145516"},{"d":"PEREN","o":"Jalukie B B.O","p":"797110","t":"BO","dl":"Delivery","c":"North Eastern Circle","r":"North East - II Region","dv":"Nagaland Division","la":"25.609973","lo":"93.665366300000002"},{"d":"PEREN","o":"Jalukiekam B.O","p":"797112","t":"BO","dl":"Delivery","c":"North Eastern Circle","r":"North East - II Region","dv":"Nagaland Division","la":"25.533872500000001","lo":"93.718644499999996"},{"d":"PEREN","o":"Khelma B.O","p":"797110","t":"BO","dl":"Delivery","c":"North Eastern Circle","r":"North East - II Region","dv":"Nagaland Division","la":"25.394444799999999","lo":"93.486651100000003"},{"d":"PEREN","o":"Lilen B.O","p":"797110","t":"BO","dl":"Delivery","c":"North Eastern Circle","r":"North East - II Region","dv":"Nagaland Division","la":"25.643905","lo":"93.598873299999994"},{"d":"PEREN","o":"Maikam B.O","p":"797103","t":"BO","dl":"Delivery","c":"North Eastern Circle","r":"North East - II Region","dv":"Nagaland Division","la":"25.769254400000001","lo":"93.687398299999998"},{"d":"PEREN","o":"Maova B.O","p":"797106","t":"BO","dl":"Delivery","c":"North Eastern Circle","r":"North East - II Region","dv":"Nagaland Division","la":"25.672847399999998","lo":"93.830794900000001"},{"d":"PEREN","o":"Mbaulwa B.O","p":"797101","t":"BO","dl":"Delivery","c":"North Eastern Circle","r":"North East - II Region","dv":"Nagaland Division","la":"25.410997800000001","lo":"93.639034800000005"},{"d":"PEREN","o":"Mhainamtsi B.O","p":"797110","t":"BO","dl":"Delivery","c":"North Eastern Circle","r":"North East - II Region","dv":"Nagaland Division","la":"25.6686549","lo":"93.703199900000001"},{"d":"PEREN","o":"Molvom B.O","p":"797106","t":"BO","dl":"Delivery","c":"North Eastern Circle","r":"North East - II Region","dv":"Nagaland Division","la":"25.711323199999999","lo":"93.829631599999999"},{"d":"PEREN","o":"N.Song B.O","p":"797101","t":"BO","dl":"Delivery","c":"North Eastern Circle","r":"North East - II Region","dv":"Nagaland Division","la":"25.281565799999999","lo":"93.549119700000006"},{"d":"PEREN","o":"Nchongram B.O","p":"797101","t":"BO","dl":"Delivery","c":"North Eastern Circle","r":"North East - II Region","dv":"Nagaland Division","la":"25.3539864","lo":"93.625329399999998"},{"d":"PEREN","o":"New Jalukie B.O","p":"797110","t":"BO","dl":"Delivery","c":"North Eastern Circle","r":"North East - II Region","dv":"Nagaland Division","la":"25.6603466","lo":"93.694213300000001"},{"d":"PEREN","o":"Peren S.O","p":"797101","t":"PO","dl":"Delivery","c":"North Eastern Circle","r":"North East - II Region","dv":"Nagaland Division","la":"25.6707778","lo":"94.1075833"},{"d":"PEREN","o":"Poilwa B.O","p":"797002","t":"BO","dl":"Delivery","c":"North Eastern Circle","r":"North East - II Region","dv":"Nagaland Division","la":"25.5809499","lo":"93.9083866"},{"d":"PEREN","o":"Punglwa B.O","p":"797106","t":"BO","dl":"Delivery","c":"North Eastern Circle","r":"North East - II Region","dv":"Nagaland Division","la":"25.6235173","lo":"93.837470800000006"},{"d":"PEREN","o":"Saijang","p":"797110","t":"BO","dl":"Delivery","c":"North Eastern Circle","r":"North East - II Region","dv":"Nagaland Division","la":"25.60403792","lo":"93.648584580000005"},{"d":"PEREN","o":"Samjiuram B.O","p":"797110","t":"BO","dl":"Delivery","c":"North Eastern Circle","r":"North East - II Region","dv":"Nagaland Division","la":"25.635051600000001","lo":"93.650086599999995"},{"d":"PEREN","o":"Tening B.O","p":"797101","t":"BO","dl":"Delivery","c":"North Eastern Circle","r":"North East - II Region","dv":"Nagaland Division","la":"25.304279000000001","lo":"93.590827899999994"},{"d":"PEREN","o":"Zalukie S.O","p":"797110","t":"PO","dl":"Delivery","c":"North Eastern Circle","r":"North East - II Region","dv":"Nagaland Division","la":"25.5124920","lo":"93.7383770"},{"d":"PHEK","o":"Akhegwo B.O","p":"797114","t":"BO","dl":"Delivery","c":"North Eastern Circle","r":"North East - II Region","dv":"Nagaland Division","la":"25.7167906","lo":"94.661396699999997"},{"d":"PHEK","o":"Chetheba B.O","p":"797104","t":"BO","dl":"Delivery","c":"North Eastern Circle","r":"North East - II Region","dv":"Nagaland Division","la":"25.667898699999999","lo":"94.262706699999995"},{"d":"PHEK","o":"Chizami Town BO","p":"797107","t":"BO","dl":"Delivery","c":"North Eastern Circle","r":"North East - II Region","dv":"Nagaland Division","la":"25.595239899999999","lo":"94.3856866"},{"d":"PHEK","o":"Chizami Village B.O","p":"797107","t":"BO","dl":"Delivery","c":"North Eastern Circle","r":"North East - II Region","dv":"Nagaland Division","la":"25.6007316","lo":"94.3935666"},{"d":"PHEK","o":"Chozuba S.O","p":"797104","t":"PO","dl":"Delivery","c":"North Eastern Circle","r":"North East - II Region","dv":"Nagaland Division","la":"25.6508120","lo":"94.3933470"},{"d":"PHEK","o":"Dzulhami B.O","p":"797104","t":"BO","dl":"Delivery","c":"North Eastern Circle","r":"North East - II Region","dv":"Nagaland Division","la":"25.827697000000001","lo":"94.387922000000003"},{"d":"PHEK","o":"Hutsu B.O","p":"797114","t":"BO","dl":"Delivery","c":"North Eastern Circle","r":"North East - II Region","dv":"Nagaland Division","la":"25.7189458","lo":"94.721591900000007"},{"d":"PHEK","o":"Ketsapo B.O","p":"797108","t":"BO","dl":"Delivery","c":"North Eastern Circle","r":"North East - II Region","dv":"Nagaland Division","la":"25.727149900000001","lo":"94.446698299999994"},{"d":"PHEK","o":"Khezhakeno B.O","p":"797107","t":"BO","dl":"Delivery","c":"North Eastern Circle","r":"North East - II Region","dv":"Nagaland Division","la":"25.515585000000002","lo":"94.209666900000002"},{"d":"PHEK","o":"Khuzami B.O","p":"797108","t":"BO","dl":"Delivery","c":"North Eastern Circle","r":"North East - II Region","dv":"Nagaland Division","la":"25.769706599999999","lo":"94.475306599999996"},{"d":"PHEK","o":"Kikruma B.O","p":"797107","t":"BO","dl":"Delivery","c":"North Eastern Circle","r":"North East - II Region","dv":"Nagaland Division","la":"25.578381799999999","lo":"94.218177499999996"},{"d":"PHEK","o":"Laruri","p":"797114","t":"BO","dl":"Delivery","c":"North Eastern Circle","r":"North East - II Region","dv":"Nagaland Division","la":"25.698912700000001","lo":"94.839749499999996"},{"d":"PHEK","o":"Lephori B.O","p":"797114","t":"BO","dl":"Delivery","c":"North Eastern Circle","r":"North East - II Region","dv":"Nagaland Division","la":"25.612263299999999","lo":"94.623459999999994"},{"d":"PHEK","o":"Losami B.O","p":"797108","t":"BO","dl":"Delivery","c":"North Eastern Circle","r":"North East - II Region","dv":"Nagaland Division","la":"25.617900500000001","lo":"94.441546000000002"},{"d":"PHEK","o":"Luzaphuhu B.O","p":"797108","t":"BO","dl":"Delivery","c":"North Eastern Circle","r":"North East - II Region","dv":"Nagaland Division","la":"25.634650000000001","lo":"94.486810000000006"},{"d":"PHEK","o":"Meluri S.O","p":"797114","t":"PO","dl":"Delivery","c":"North Eastern Circle","r":"North East - II Region","dv":"Nagaland Division","la":"25.6508120","lo":"94.3933470"},{"d":"PHEK","o":"Mesolumi B.O","p":"797107","t":"BO","dl":"Delivery","c":"North Eastern Circle","r":"North East - II Region","dv":"Nagaland Division","la":"25.5794666","lo":"94.3427583"},{"d":"PHEK","o":"Middle Khomi B.O","p":"797108","t":"BO","dl":"Delivery","c":"North Eastern Circle","r":"North East - II Region","dv":"Nagaland Division","la":"25.657148299999999","lo":"94.400006599999998"},{"d":"PHEK","o":"Old Phek B.O","p":"797108","t":"BO","dl":"Delivery","c":"North Eastern Circle","r":"North East - II Region","dv":"Nagaland Division","la":"25.665884999999999","lo":"94.468414999999993"},{"d":"PHEK","o":"Pfutsero S.O","p":"797107","t":"PO","dl":"Delivery","c":"North Eastern Circle","r":"North East - II Region","dv":"Nagaland Division","la":"25.6508120","lo":"94.3933470"},{"d":"PHEK","o":"Phek S.O","p":"797108","t":"PO","dl":"Delivery","c":"North Eastern Circle","r":"North East - II Region","dv":"Nagaland Division","la":"25.7077","lo":"94.4616"},{"d":"PHEK","o":"Phesachuduma B.O","p":"797107","t":"BO","dl":"Delivery","c":"North Eastern Circle","r":"North East - II Region","dv":"Nagaland Division","la":"25.607720700000002","lo":"94.253179700000004"},{"d":"PHEK","o":"Phugwu B.O","p":"797104","t":"BO","dl":"Delivery","c":"North Eastern Circle","r":"North East - II Region","dv":"Nagaland Division","la":"25.776123999999999","lo":"94.399078000000003"},{"d":"PHEK","o":"Porba B.O","p":"797107","t":"BO","dl":"Delivery","c":"North Eastern Circle","r":"North East - II Region","dv":"Nagaland Division","la":"25.615311899999998","lo":"94.335838499999994"},{"d":"PHEK","o":"Pungkhuri B.O","p":"797114","t":"BO","dl":"Delivery","c":"North Eastern Circle","r":"North East - II Region","dv":"Nagaland Division","la":"25.606058300000001","lo":"94.835178299999995"},{"d":"PHEK","o":"Reguri","p":"797114","t":"BO","dl":"Delivery","c":"North Eastern Circle","r":"North East - II Region","dv":"Nagaland Division","la":"25.537185300000001","lo":"94.659243200000006"},{"d":"PHEK","o":"Runguzumi B.O","p":"797104","t":"BO","dl":"Delivery","c":"North Eastern Circle","r":"North East - II Region","dv":"Nagaland Division","la":"25.682375","lo":"94.300622000000004"},{"d":"PHEK","o":"Ruzazho","p":"797104","t":"BO","dl":"Delivery","c":"North Eastern Circle","r":"North East - II Region","dv":"Nagaland Division","la":"25.7471742","lo":"94.419851300000005"},{"d":"PHEK","o":"Sakraba B.O","p":"797107","t":"BO","dl":"Delivery","c":"North Eastern Circle","r":"North East - II Region","dv":"Nagaland Division","la":"25.6257333","lo":"94.368521599999994"},{"d":"PHEK","o":"Tekhouba B.O","p":"797107","t":"BO","dl":"Delivery","c":"North Eastern Circle","r":"North East - II Region","dv":"Nagaland Division","la":"25.559336299999998","lo":"94.2845291"},{"d":"PHEK","o":"Thechulumi B.O","p":"797107","t":"BO","dl":"Delivery","c":"North Eastern Circle","r":"North East - II Region","dv":"Nagaland Division","la":"25.551263299999999","lo":"94.397388300000003"},{"d":"PHEK","o":"Thenizumi B.O","p":"797104","t":"BO","dl":"Delivery","c":"North Eastern Circle","r":"North East - II Region","dv":"Nagaland Division","la":"25.653362000000001","lo":"94.255157999999994"},{"d":"PHEK","o":"Thevophisumi B.O","p":"797104","t":"BO","dl":"Delivery","c":"North Eastern Circle","r":"North East - II Region","dv":"Nagaland Division","la":"25.696731","lo":"94.320687000000007"},{"d":"PHEK","o":"Thipuzumi B.O","p":"797107","t":"BO","dl":"Delivery","c":"North Eastern Circle","r":"North East - II Region","dv":"Nagaland Division","la":"25.626529999999999","lo":"94.267804999999996"},{"d":"PHEK","o":"Wazhiho B.O","p":"797114","t":"BO","dl":"Delivery","c":"North Eastern Circle","r":"North East - II Region","dv":"Nagaland Division","la":"25.6662222","lo":"94.716831099999993"},{"d":"PHEK","o":"Yorubami B.O","p":"797104","t":"BO","dl":"Delivery","c":"North Eastern Circle","r":"North East - II Region","dv":"Nagaland Division","la":"25.738844","lo":"94.338093999999998"},{"d":"PHEK","o":"Zavame B.O","p":"797107","t":"BO","dl":"Delivery","c":"North Eastern Circle","r":"North East - II Region","dv":"Nagaland Division","la":"25.512559899999999","lo":"94.313804899999994"},{"d":"PHEK","o":"Zeloma","p":"797107","t":"BO","dl":"Delivery","c":"North Eastern Circle","r":"North East - II Region","dv":"Nagaland Division","la":"25.520409999999998","lo":"94.337050000000005"},{"d":"PHEK","o":"Zuketsa B.O","p":"797107","t":"BO","dl":"Delivery","c":"North Eastern Circle","r":"North East - II Region","dv":"Nagaland Division","la":"25.535971700000001","lo":"94.2373008"},{"d":"TUENSANG","o":"Angangba B.O","p":"798616","t":"BO","dl":"Delivery","c":"North Eastern Circle","r":"North East - II Region","dv":"Nagaland Division","la":"26.217474200000002","lo":"94.680831800000007"},{"d":"TUENSANG","o":"Aniashu","p":"798612","t":"BO","dl":"Delivery","c":"North Eastern Circle","r":"North East - II Region","dv":"Nagaland Division","la":"26.158237","lo":"95.072081999999995"},{"d":"TUENSANG","o":"Chare B.O","p":"798601","t":"BO","dl":"Delivery","c":"North Eastern Circle","r":"North East - II Region","dv":"Nagaland Division","la":"26.289238300000001","lo":"94.622381599999997"},{"d":"TUENSANG","o":"Chasser","p":"798628","t":"BO","dl":"Delivery","c":"North Eastern Circle","r":"North East - II Region","dv":"Nagaland Division","la":"26.10574218","lo":"94.79793987"},{"d":"TUENSANG","o":"Chendang","p":"798612","t":"BO","dl":"Delivery","c":"North Eastern Circle","r":"North East - II Region","dv":"Nagaland Division","la":"26.194330000000001","lo":"94.850830000000002"},{"d":"TUENSANG","o":"Chessore B.O","p":"798628","t":"BO","dl":"Delivery","c":"North Eastern Circle","r":"North East - II Region","dv":"Nagaland Division","la":"26.08892","lo":"94.7445483"},{"d":"TUENSANG","o":"Chilliso","p":"798612","t":"BO","dl":"Delivery","c":"North Eastern Circle","r":"North East - II Region","dv":"Nagaland Division","la":"26.012747000000001","lo":"94.935874999999996"},{"d":"TUENSANG","o":"Chimonger B.O","p":"798616","t":"BO","dl":"Delivery","c":"North Eastern Circle","r":"North East - II Region","dv":"Nagaland Division","la":"26.278386000000001","lo":"94.677397799999994"},{"d":"TUENSANG","o":"Chipur","p":"798612","t":"BO","dl":"Delivery","c":"North Eastern Circle","r":"North East - II Region","dv":"Nagaland Division","la":"25.989082679999999","lo":"94.984640119999995"},{"d":"TUENSANG","o":"Chungtore B.O","p":"798616","t":"BO","dl":"Delivery","c":"North Eastern Circle","r":"North East - II Region","dv":"Nagaland Division","la":"26.2374011","lo":"94.695998000000003"},{"d":"TUENSANG","o":"Hak","p":"798612","t":"BO","dl":"Delivery","c":"North Eastern Circle","r":"North East - II Region","dv":"Nagaland Division","la":"26.30599552","lo":"94.772864369999994"},{"d":"TUENSANG","o":"Hakchang","p":"798612","t":"BO","dl":"Delivery","c":"North Eastern Circle","r":"North East - II Region","dv":"Nagaland Division","la":"26.301929999999999","lo":"94.848889999999997"},{"d":"TUENSANG","o":"Huker B.O","p":"798628","t":"BO","dl":"Delivery","c":"North Eastern Circle","r":"North East - II Region","dv":"Nagaland Division","la":"26.0502401","lo":"94.6952443"},{"d":"TUENSANG","o":"Kenjong","p":"798612","t":"BO","dl":"Delivery","c":"North Eastern Circle","r":"North East - II Region","dv":"Nagaland Division","la":"26.01272329","lo":"95.025292199999996"},{"d":"TUENSANG","o":"Khudei","p":"798612","t":"BO","dl":"Delivery","c":"North Eastern Circle","r":"North East - II Region","dv":"Nagaland Division","la":"26.304739999999999","lo":"94.784729999999996"},{"d":"TUENSANG","o":"Kingniu","p":"798612","t":"BO","dl":"Delivery","c":"North Eastern Circle","r":"North East - II Region","dv":"Nagaland Division","la":"26.1152193","lo":"94.960714300000006"},{"d":"TUENSANG","o":"Kiutsukiur","p":"798628","t":"BO","dl":"Delivery","c":"North Eastern Circle","r":"North East - II Region","dv":"Nagaland Division","la":"26.045668","lo":"94.749939"},{"d":"TUENSANG","o":"Kongsang B.O","p":"798612","t":"BO","dl":"Delivery","c":"North Eastern Circle","r":"North East - II Region","dv":"Nagaland Division","la":"26.398959999999999","lo":"94.771744999999996"},{"d":"TUENSANG","o":"Konya","p":"798612","t":"BO","dl":"Delivery","c":"North Eastern Circle","r":"North East - II Region","dv":"Nagaland Division","la":"26.265955000000002","lo":"94.863022000000001"},{"d":"TUENSANG","o":"Kuthur B.O","p":"798628","t":"BO","dl":"Delivery","c":"North Eastern Circle","r":"North East - II Region","dv":"Nagaland Division","la":"26.1767983","lo":"94.81397"},{"d":"TUENSANG","o":"Langnok","p":"798612","t":"BO","dl":"Delivery","c":"North Eastern Circle","r":"North East - II Region","dv":"Nagaland Division","la":"26.190442900000001","lo":"95.046638000000002"},{"d":"TUENSANG","o":"Longkhim S.O","p":"798616","t":"PO","dl":"Delivery","c":"North Eastern Circle","r":"North East - II Region","dv":"Nagaland Division","la":"24.7513890","lo":"78.8378330"},{"d":"TUENSANG","o":"Longtang","p":"798612","t":"BO","dl":"Delivery","c":"North Eastern Circle","r":"North East - II Region","dv":"Nagaland Division","la":"26.3297466","lo":"94.743693039999997"},{"d":"TUENSANG","o":"Longtokur","p":"798628","t":"BO","dl":"Delivery","c":"North Eastern Circle","r":"North East - II Region","dv":"Nagaland Division","la":"26.13740248","lo":"94.6968533"},{"d":"TUENSANG","o":"Noksen B.O","p":"798612","t":"BO","dl":"Delivery","c":"North Eastern Circle","r":"North East - II Region","dv":"Nagaland Division","la":"26.3706599","lo":"94.713873300000003"},{"d":"TUENSANG","o":"Rurur AB","p":"798628","t":"BO","dl":"Delivery","c":"North Eastern Circle","r":"North East - II Region","dv":"Nagaland Division","la":"26.00664912","lo":"94.79900029"},{"d":"TUENSANG","o":"Sangsanyu B.O","p":"798612","t":"BO","dl":"Delivery","c":"North Eastern Circle","r":"North East - II Region","dv":"Nagaland Division","la":"26.327422800000001","lo":"94.893279800000002"},{"d":"TUENSANG","o":"Sangtak","p":"798612","t":"BO","dl":"Delivery","c":"North Eastern Circle","r":"North East - II Region","dv":"Nagaland Division","la":"26.235742200000001","lo":"94.813186299999998"},{"d":"TUENSANG","o":"Saoshou","p":"798612","t":"BO","dl":"Delivery","c":"North Eastern Circle","r":"North East - II Region","dv":"Nagaland Division","la":"26.367586750000001","lo":"94.889514599999998"},{"d":"TUENSANG","o":"Saramati B.O","p":"798612","t":"BO","dl":"Delivery","c":"North Eastern Circle","r":"North East - II Region","dv":"Nagaland Division","la":"26.2397378","lo":"94.798214599999994"},{"d":"TUENSANG","o":"Shamator B.O","p":"798612","t":"BO","dl":"Delivery","c":"North Eastern Circle","r":"North East - II Region","dv":"Nagaland Division","la":"26.073306599999999","lo":"94.869834999999995"},{"d":"TUENSANG","o":"Shampur B.O","p":"798628","t":"BO","dl":"Delivery","c":"North Eastern Circle","r":"North East - II Region","dv":"Nagaland Division","la":"26.1640212","lo":"94.8441158"},{"d":"TUENSANG","o":"Shiponger B.O","p":"798628","t":"BO","dl":"Delivery","c":"North Eastern Circle","r":"North East - II Region","dv":"Nagaland Division","la":"26.2274333","lo":"94.809315"},{"d":"TUENSANG","o":"Sipongsang","p":"798612","t":"BO","dl":"Delivery","c":"North Eastern Circle","r":"North East - II Region","dv":"Nagaland Division","la":"26.412949999999999","lo":"94.811959999999999"},{"d":"TUENSANG","o":"Sotokur B.O","p":"798628","t":"BO","dl":"Delivery","c":"North Eastern Circle","r":"North East - II Region","dv":"Nagaland Division","la":"26.1535083","lo":"94.7681533"},{"d":"TUENSANG","o":"Taknyu","p":"798612","t":"BO","dl":"Delivery","c":"North Eastern Circle","r":"North East - II Region","dv":"Nagaland Division","la":"26.272424900000001","lo":"94.984763999999998"},{"d":"TUENSANG","o":"Tronger B.O","p":"798601","t":"BO","dl":"Delivery","c":"North Eastern Circle","r":"North East - II Region","dv":"Nagaland Division","la":"26.2719816","lo":"94.6350166"},{"d":"TUENSANG","o":"Tuensang S.O","p":"798612","t":"PO","dl":"Delivery","c":"North Eastern Circle","r":"North East - II Region","dv":"Nagaland Division","la":"26.23380556","lo":"94.81158333"},{"d":"TUENSANG","o":"Tuensang Village B.O","p":"798612","t":"BO","dl":"Delivery","c":"North Eastern Circle","r":"North East - II Region","dv":"Nagaland Division","la":"26.2377857","lo":"94.813247500000003"},{"d":"TUENSANG","o":"Yangli B.O","p":"798616","t":"BO","dl":"Delivery","c":"North Eastern Circle","r":"North East - II Region","dv":"Nagaland Division","la":"26.208690399999998","lo":"94.655316999999997"},{"d":"TUENSANG","o":"Yimpang","p":"798612","t":"BO","dl":"Delivery","c":"North Eastern Circle","r":"North East - II Region","dv":"Nagaland Division","la":"26.272445999999999","lo":"94.957901000000007"},{"d":"WOKHA","o":"Aitepyong B.O","p":"797111","t":"BO","dl":"Delivery","c":"North Eastern Circle","r":"North East - II Region","dv":"Nagaland Division","la":"26.325156700000001","lo":"94.512258500000002"},{"d":"WOKHA","o":"Arree Old B.O","p":"798607","t":"BO","dl":"Delivery","c":"North Eastern Circle","r":"North East - II Region","dv":"Nagaland Division","la":"26.198187099999998","lo":"94.330554899999996"},{"d":"WOKHA","o":"Baghty B.O","p":"797111","t":"BO","dl":"Delivery","c":"North Eastern Circle","r":"North East - II Region","dv":"Nagaland Division","la":"26.241308799999999","lo":"94.194323400000002"},{"d":"WOKHA","o":"Bhandari S.O","p":"797099","t":"PO","dl":"Delivery","c":"North Eastern Circle","r":"North East - II Region","dv":"Nagaland Division","la":"26.2849592","lo":"94.1118263"},{"d":"WOKHA","o":"Chukitong B.O","p":"797111","t":"BO","dl":"Delivery","c":"North Eastern Circle","r":"North East - II Region","dv":"Nagaland Division","la":"26.108491999999998","lo":"94.295266699999999"},{"d":"WOKHA","o":"Doyang BO","p":"797111","t":"BO","dl":"Delivery","c":"North Eastern Circle","r":"North East - II Region","dv":"Nagaland Division","la":"26.2228849","lo":"94.247298299999997"},{"d":"WOKHA","o":"Elumnyu B.O","p":"797111","t":"BO","dl":"Delivery","c":"North Eastern Circle","r":"North East - II Region","dv":"Nagaland Division","la":"25.674131599999999","lo":"94.111596599999999"},{"d":"WOKHA","o":"Englan B.O","p":"797111","t":"BO","dl":"Delivery","c":"North Eastern Circle","r":"North East - II Region","dv":"Nagaland Division","la":"26.1720054","lo":"94.251177900000002"},{"d":"WOKHA","o":"Humtsu B.O","p":"797111","t":"BO","dl":"Delivery","c":"North Eastern Circle","r":"North East - II Region","dv":"Nagaland Division","la":"26.097653300000001","lo":"94.252705000000006"},{"d":"WOKHA","o":"Liowokha Old","p":"797099","t":"BO","dl":"Delivery","c":"North Eastern Circle","r":"North East - II Region","dv":"Nagaland Division","la":"26.095193200000001","lo":"94.255914700000005"},{"d":"WOKHA","o":"Longtsung B.O","p":"797111","t":"BO","dl":"Delivery","c":"North Eastern Circle","r":"North East - II Region","dv":"Nagaland Division","la":"26.100798999999999","lo":"94.097961100000006"},{"d":"WOKHA","o":"Lotsu B.O","p":"797111","t":"BO","dl":"Delivery","c":"North Eastern Circle","r":"North East - II Region","dv":"Nagaland Division","la":"26.074872800000001","lo":"94.077134299999997"},{"d":"WOKHA","o":"Mekhukla B.O","p":"797111","t":"BO","dl":"Delivery","c":"North Eastern Circle","r":"North East - II Region","dv":"Nagaland Division","la":"26.3509733","lo":"94.311754899999997"},{"d":"WOKHA","o":"Moilan B.O","p":"797111","t":"BO","dl":"Delivery","c":"North Eastern Circle","r":"North East - II Region","dv":"Nagaland Division","la":"26.0594766","lo":"94.062768300000002"},{"d":"WOKHA","o":"N. Longidong B.O","p":"797111","t":"BO","dl":"Delivery","c":"North Eastern Circle","r":"North East - II Region","dv":"Nagaland Division","la":"26.030746600000001","lo":"94.332207400000001"},{"d":"WOKHA","o":"Nyiro B.O","p":"797111","t":"BO","dl":"Delivery","c":"North Eastern Circle","r":"North East - II Region","dv":"Nagaland Division","la":"26.069724999999998","lo":"94.286274899999995"},{"d":"WOKHA","o":"Pangti B.O","p":"797111","t":"BO","dl":"Delivery","c":"North Eastern Circle","r":"North East - II Region","dv":"Nagaland Division","la":"26.2597852","lo":"94.320242500000006"},{"d":"WOKHA","o":"Pongitong B.O","p":"797111","t":"BO","dl":"Delivery","c":"North Eastern Circle","r":"North East - II Region","dv":"Nagaland Division","la":"26.0517483","lo":"94.206214200000005"},{"d":"WOKHA","o":"Ralan B.O","p":"797112","t":"BO","dl":"Delivery","c":"North Eastern Circle","r":"North East - II Region","dv":"Nagaland Division","la":"25.977309300000002","lo":"93.960013000000004"},{"d":"WOKHA","o":"Sanis B.O","p":"797111","t":"BO","dl":"Delivery","c":"North Eastern Circle","r":"North East - II Region","dv":"Nagaland Division","la":"26.222506599999999","lo":"94.219043299999996"},{"d":"WOKHA","o":"Sungro B.O","p":"797111","t":"BO","dl":"Delivery","c":"North Eastern Circle","r":"North East - II Region","dv":"Nagaland Division","la":"26.269433299999999","lo":"94.335475000000002"},{"d":"WOKHA","o":"Tsungtsutong B.O","p":"797111","t":"BO","dl":"Delivery","c":"North Eastern Circle","r":"North East - II Region","dv":"Nagaland Division","la":"26.059002","lo":"94.242164799999998"},{"d":"WOKHA","o":"Wokha S.O","p":"797111","t":"PO","dl":"Delivery","c":"North Eastern Circle","r":"North East - II Region","dv":"Nagaland Division","la":"26.0942","lo":"94.2599"},{"d":"WOKHA","o":"Wokha Village B.O","p":"797111","t":"BO","dl":"Delivery","c":"North Eastern Circle","r":"North East - II Region","dv":"Nagaland Division","la":"26.109780000000001","lo":"94.252238899999995"},{"d":"WOKHA","o":"Wozhu Old","p":"797099","t":"BO","dl":"Delivery","c":"North Eastern Circle","r":"North East - II Region","dv":"Nagaland Division","la":"26.394059120000001","lo":"94.22816736"},{"d":"WOKHA","o":"Wozhuro B.O","p":"797111","t":"BO","dl":"Delivery","c":"North Eastern Circle","r":"North East - II Region","dv":"Nagaland Division","la":"25.997453700000001","lo":"94.1594537"},{"d":"WOKHA","o":"Yamhon B.O","p":"797111","t":"BO","dl":"Delivery","c":"North Eastern Circle","r":"North East - II Region","dv":"Nagaland Division","la":"26.122951700000002","lo":"94.049964200000005"},{"d":"WOKHA","o":"Yampha B.O","p":"797112","t":"BO","dl":"Delivery","c":"North Eastern Circle","r":"North East - II Region","dv":"Nagaland Division","la":"25.983391699999999","lo":"93.962567699999994"},{"d":"WOKHA","o":"Yikhum B.O","p":"797111","t":"BO","dl":"Delivery","c":"North Eastern Circle","r":"North East - II Region","dv":"Nagaland Division","la":"26.148306699999999","lo":"94.219780200000002"},{"d":"ZUNHEBOTO","o":"Aghunato B.O","p":"798620","t":"BO","dl":"Delivery","c":"North Eastern Circle","r":"North East - II Region","dv":"Nagaland Division","la":"26.010072300000001","lo":"94.633133900000004"},{"d":"ZUNHEBOTO","o":"Aizuto B.O","p":"798627","t":"BO","dl":"Delivery","c":"North Eastern Circle","r":"North East - II Region","dv":"Nagaland Division","la":"26.148995299999999","lo":"94.525448499999996"},{"d":"ZUNHEBOTO","o":"Akuhaito B.O","p":"798620","t":"BO","dl":"Delivery","c":"North Eastern Circle","r":"North East - II Region","dv":"Nagaland Division","la":"26.081222799999999","lo":"94.456054199999997"},{"d":"ZUNHEBOTO","o":"Akuluto B.O","p":"798627","t":"BO","dl":"Delivery","c":"North Eastern Circle","r":"North East - II Region","dv":"Nagaland Division","la":"26.166711599999999","lo":"94.488137199999997"},{"d":"ZUNHEBOTO","o":"Asukhomi B.O","p":"798620","t":"BO","dl":"Delivery","c":"North Eastern Circle","r":"North East - II Region","dv":"Nagaland Division","la":"26.071092","lo":"94.523392200000004"},{"d":"ZUNHEBOTO","o":"Asukuto B.O","p":"798620","t":"BO","dl":"Delivery","c":"North Eastern Circle","r":"North East - II Region","dv":"Nagaland Division","la":"26.094728400000001","lo":"94.4947157"},{"d":"ZUNHEBOTO","o":"Asuto B.O","p":"798620","t":"BO","dl":"Delivery","c":"North Eastern Circle","r":"North East - II Region","dv":"Nagaland Division","la":"26.114384900000001","lo":"94.630097199999994"},{"d":"ZUNHEBOTO","o":"Atoizu B.O","p":"798620","t":"BO","dl":"Delivery","c":"North Eastern Circle","r":"North East - II Region","dv":"Nagaland Division","la":"26.109604999999998","lo":"94.516431900000001"},{"d":"ZUNHEBOTO","o":"Ghathashi B.O","p":"797109","t":"BO","dl":"Delivery","c":"North Eastern Circle","r":"North East - II Region","dv":"Nagaland Division","la":"25.848273299999999","lo":"94.327889999999996"},{"d":"ZUNHEBOTO","o":"Ghokhuvi","p":"798620","t":"BO","dl":"Delivery","c":"North Eastern Circle","r":"North East - II Region","dv":"Nagaland Division","la":"25.848082000000002","lo":"94.531341999999995"},{"d":"ZUNHEBOTO","o":"Hokiye","p":"798620","t":"BO","dl":"Delivery","c":"North Eastern Circle","r":"North East - II Region","dv":"Nagaland Division","la":"25.761590999999999","lo":"94.562438999999998"},{"d":"ZUNHEBOTO","o":"Hosephu B.O","p":"798620","t":"BO","dl":"Delivery","c":"North Eastern Circle","r":"North East - II Region","dv":"Nagaland Division","la":"25.900086600000002","lo":"94.555483300000006"},{"d":"ZUNHEBOTO","o":"Keltomi","p":"798620","t":"BO","dl":"Delivery","c":"North Eastern Circle","r":"North East - II Region","dv":"Nagaland Division","la":"26.03777333","lo":"94.611950289999996"},{"d":"ZUNHEBOTO","o":"Khetoi","p":"798620","t":"BO","dl":"Delivery","c":"North Eastern Circle","r":"North East - II Region","dv":"Nagaland Division","la":"25.939333000000001","lo":"94.564430000000002"},{"d":"ZUNHEBOTO","o":"Khukishe","p":"798620","t":"BO","dl":"Delivery","c":"North Eastern Circle","r":"North East - II Region","dv":"Nagaland Division","la":"25.951385999999999","lo":"94.534026999999995"},{"d":"ZUNHEBOTO","o":"Kichilimi B.O","p":"798620","t":"BO","dl":"Delivery","c":"North Eastern Circle","r":"North East - II Region","dv":"Nagaland Division","la":"25.9408067","lo":"94.345552400000003"},{"d":"ZUNHEBOTO","o":"Kilomi B.O","p":"797104","t":"BO","dl":"Delivery","c":"North Eastern Circle","r":"North East - II Region","dv":"Nagaland Division","la":"25.864281999999999","lo":"94.416407000000007"},{"d":"ZUNHEBOTO","o":"Kivikhu","p":"798620","t":"BO","dl":"Delivery","c":"North Eastern Circle","r":"North East - II Region","dv":"Nagaland Division","la":"25.840031","lo":"94.479904000000005"},{"d":"ZUNHEBOTO","o":"Lazami B.O","p":"797109","t":"BO","dl":"Delivery","c":"North Eastern Circle","r":"North East - II Region","dv":"Nagaland Division","la":"25.856114999999999","lo":"94.246926599999995"},{"d":"ZUNHEBOTO","o":"Lukhuyimi","p":"798620","t":"BO","dl":"Delivery","c":"North Eastern Circle","r":"North East - II Region","dv":"Nagaland Division","la":"26.03068231","lo":"94.586908559999998"},{"d":"ZUNHEBOTO","o":"Lumami S.O","p":"798627","t":"PO","dl":"Delivery","c":"North Eastern Circle","r":"North East - II Region","dv":"Nagaland Division","la":"26.1630160","lo":"94.5416790"},{"d":"ZUNHEBOTO","o":"Luthsumi","p":"798620","t":"BO","dl":"Delivery","c":"North Eastern Circle","r":"North East - II Region","dv":"Nagaland Division","la":"26.041906149999999","lo":"94.585901460000002"},{"d":"ZUNHEBOTO","o":"Luvishe New","p":"798620","t":"BO","dl":"Delivery","c":"North Eastern Circle","r":"North East - II Region","dv":"Nagaland Division","la":"25.985658900000001","lo":"94.597549999999998"},{"d":"ZUNHEBOTO","o":"Mishilimi B.O","p":"797105","t":"BO","dl":"Delivery","c":"North Eastern Circle","r":"North East - II Region","dv":"Nagaland Division","la":"25.887505000000001","lo":"94.261749899999998"},{"d":"ZUNHEBOTO","o":"Pughoboto B.O","p":"797109","t":"BO","dl":"Delivery","c":"North Eastern Circle","r":"North East - II Region","dv":"Nagaland Division","la":"25.891221600000002","lo":"94.268169999999998"},{"d":"ZUNHEBOTO","o":"Roto Old","p":"798620","t":"BO","dl":"Delivery","c":"North Eastern Circle","r":"North East - II Region","dv":"Nagaland Division","la":"26.069445000000002","lo":"94.421456000000006"},{"d":"ZUNHEBOTO","o":"Saghemi B.O","p":"798620","t":"BO","dl":"Delivery","c":"North Eastern Circle","r":"North East - II Region","dv":"Nagaland Division","la":"26.112750399999999","lo":"94.558318799999995"},{"d":"ZUNHEBOTO","o":"Satakha B.O","p":"798620","t":"BO","dl":"Delivery","c":"North Eastern Circle","r":"North East - II Region","dv":"Nagaland Division","la":"25.938009999999998","lo":"94.441999999999993"},{"d":"ZUNHEBOTO","o":"Satami B.O","p":"798620","t":"BO","dl":"Delivery","c":"North Eastern Circle","r":"North East - II Region","dv":"Nagaland Division","la":"26.091411900000001","lo":"94.620864900000001"},{"d":"ZUNHEBOTO","o":"Satoi B.O","p":"798620","t":"BO","dl":"Delivery","c":"North Eastern Circle","r":"North East - II Region","dv":"Nagaland Division","la":"25.831887099999999","lo":"94.575941"},{"d":"ZUNHEBOTO","o":"Shesulimi","p":"798620","t":"BO","dl":"Delivery","c":"North Eastern Circle","r":"North East - II Region","dv":"Nagaland Division","la":"25.901565999999999","lo":"94.326003999999998"},{"d":"ZUNHEBOTO","o":"Suruhuto B.O","p":"798620","t":"BO","dl":"Delivery","c":"North Eastern Circle","r":"North East - II Region","dv":"Nagaland Division","la":"26.096025300000001","lo":"94.627659399999999"},{"d":"ZUNHEBOTO","o":"Surumi B.O","p":"798620","t":"BO","dl":"Delivery","c":"North Eastern Circle","r":"North East - II Region","dv":"Nagaland Division","la":"26.1553547","lo":"94.562518900000001"},{"d":"ZUNHEBOTO","o":"Thakiye","p":"798620","t":"BO","dl":"Delivery","c":"North Eastern Circle","r":"North East - II Region","dv":"Nagaland Division","la":"25.802078000000002","lo":"94.617462000000003"},{"d":"ZUNHEBOTO","o":"Tokiye B.O","p":"798620","t":"BO","dl":"Delivery","c":"North Eastern Circle","r":"North East - II Region","dv":"Nagaland Division","la":"26.0180045","lo":"94.581369899999999"},{"d":"ZUNHEBOTO","o":"Tukuliqa","p":"798620","t":"BO","dl":"Delivery","c":"North Eastern Circle","r":"North East - II Region","dv":"Nagaland Division","la":"25.815812999999999","lo":"94.293639999999996"},{"d":"ZUNHEBOTO","o":"V. K. Town B.O","p":"798601","t":"BO","dl":"Delivery","c":"North Eastern Circle","r":"North East - II Region","dv":"Nagaland Division","la":"26.182542999999999","lo":"94.413783600000002"},{"d":"ZUNHEBOTO","o":"Xuivi","p":"798620","t":"BO","dl":"Delivery","c":"North Eastern Circle","r":"North East - II Region","dv":"Nagaland Division","la":"25.887803999999999","lo":"94.449614999999994"},{"d":"ZUNHEBOTO","o":"Xukhepu","p":"798620","t":"BO","dl":"Delivery","c":"North Eastern Circle","r":"North East - II Region","dv":"Nagaland Division","la":"25.982634900000001","lo":"94.450553999999997"},{"d":"ZUNHEBOTO","o":"Yehemi","p":"798620","t":"BO","dl":"Delivery","c":"North Eastern Circle","r":"North East - II Region","dv":"Nagaland Division","la":"26.147396000000001","lo":"94.608649999999997"},{"d":"ZUNHEBOTO","o":"Yevishe","p":"798620","t":"BO","dl":"Delivery","c":"North Eastern Circle","r":"North East - II Region","dv":"Nagaland Division","la":"26.128177900000001","lo":"94.660522999999998"},{"d":"ZUNHEBOTO","o":"Zunheboto S.O","p":"798620","t":"PO","dl":"Delivery","c":"North Eastern Circle","r":"North East - II Region","dv":"Nagaland Division","la":"26.01333333","lo":"94.52644444"}]